Metadata-Version: 2.1
Name: ALazyQiwi
Version: 1.2
Summary: Simple async library for qiwi farms
Home-page: UNKNOWN
License: UNKNOWN
Platform: UNKNOWN
Requires-Python: >=3.10
